python_nhc/__init__.py
python_nhc/nhc_action.py
python_nhc/nhc_connection.py
python_nhc/python_nhc.py
python_nhc-0.2.0.dist-info/LICENSE
python_nhc-0.2.0.dist-info/WHEEL
python_nhc-0.2.0.dist-info/METADATA
python_nhc-0.2.0.dist-info/RECORD
